RsCMPX_BluetoothMeas/RsCMPX_BluetoothMeas.py
RsCMPX_BluetoothMeas/__init__.py
RsCMPX_BluetoothMeas/enums.py
RsCMPX_BluetoothMeas/repcap.py
RsCMPX_BluetoothMeas/CustomFiles/__init__.py
RsCMPX_BluetoothMeas/CustomFiles/events.py
RsCMPX_BluetoothMeas/CustomFiles/reliability.py
RsCMPX_BluetoothMeas/CustomFiles/utilities.py
RsCMPX_BluetoothMeas/Implementations/__init__.py
RsCMPX_BluetoothMeas/Implementations/Bluetooth/__init__.py
RsCMPX_BluetoothMeas/Implementations/Bluetooth/Measurement/__init__.py
RsCMPX_BluetoothMeas/Implementations/Bluetooth/Measurement/BhRate/__init__.py
RsCMPX_BluetoothMeas/Implementations/Bluetooth/Measurement/BhRate/InputSignal/__init__.py
RsCMPX_BluetoothMeas/Implementations/Bluetooth/Measurement/BhRate/InputSignal/Adetected/Plength.py
RsCMPX_BluetoothMeas/Implementations/Bluetooth/Measurement/BhRate/InputSignal/Adetected/Ptype.py
RsCMPX_BluetoothMeas/Implementations/Bluetooth/Measurement/BhRate/InputSignal/Adetected/__init__.py
RsCMPX_BluetoothMeas/Implementations/Bluetooth/Measurement/BhRate/Modulation/Average.py
RsCMPX_BluetoothMeas/Implementations/Bluetooth/Measurement/BhRate/Modulation/Current.py
RsCMPX_BluetoothMeas/Implementations/Bluetooth/Measurement/BhRate/Modulation/Maximum.py
RsCMPX_BluetoothMeas/Implementations/Bluetooth/Measurement/BhRate/Modulation/StandardDev.py
RsCMPX_BluetoothMeas/Implementations/Bluetooth/Measurement/BhRate/Modulation/__init__.py
RsCMPX_BluetoothMeas/Implementations/Bluetooth/Measurement/BhRate/Pencoding/Current.py
RsCMPX_BluetoothMeas/Implementations/Bluetooth/Measurement/BhRate/Pencoding/__init__.py
RsCMPX_BluetoothMeas/Implementations/Bluetooth/Measurement/BhRate/PowerVsTime/Average.py
RsCMPX_BluetoothMeas/Implementations/Bluetooth/Measurement/BhRate/PowerVsTime/Current.py
RsCMPX_BluetoothMeas/Implementations/Bluetooth/Measurement/BhRate/PowerVsTime/Maximum.py
RsCMPX_BluetoothMeas/Implementations/Bluetooth/Measurement/BhRate/PowerVsTime/Minimum.py
RsCMPX_BluetoothMeas-5.0.70.dist-info/METADATA
RsCMPX_BluetoothMeas-5.0.70.dist-info/WHEEL
RsCMPX_BluetoothMeas-5.0.70.dist-info/top_level.txt
RsCMPX_BluetoothMeas-5.0.70.dist-info/RECORD
